ai_oppose/__init__.py
ai_oppose/functions.py
ai_oppose/data/egodepletion_literature.csv
ai_oppose/data/humorXdating_literature.csv
ai_oppose/data/mutualism_literature.csv
ai_oppose/data/powerpose_literature.csv
ai_oppose-0.0.15.dist-info/METADATA
ai_oppose-0.0.15.dist-info/WHEEL
ai_oppose-0.0.15.dist-info/top_level.txt
ai_oppose-0.0.15.dist-info/RECORD
