Metadata-Version: 2.1
Name: ai-oppose
Version: 0.0.15
Summary: generating adversarial takes on science claims with openai plus vectorstores
Home-page: https://github.com/hannesrosenbusch/ai_oppose
Author: Hannes Rosenbusch
Author-email: h.rosenbusch@uva.nl
Classifier: Programming Language :: Python :: 3
Classifier: License :: OSI Approved :: MIT License
Classifier: Operating System :: OS Independent
Requires-Python: >=3.9
Requires-Dist: google-search-results ==2.4.2
Requires-Dist: googlesearch-python ==1.2.3
Requires-Dist: litstudy ==1.0.5
Requires-Dist: scholarly ==1.7.11
Requires-Dist: selenium ==4.11.2
Requires-Dist: reportlab ==4.0.4
Requires-Dist: fuzzywuzzy ==0.18.0
Requires-Dist: PyPDF2 ==3.0.1
Requires-Dist: chromadb ==0.4.5
Requires-Dist: langchain ==0.0.257
Requires-Dist: tiktoken ==0.4.0
Requires-Dist: Unidecode ==1.3.6
Requires-Dist: unstructured ==0.9.0
Requires-Dist: openai ==0.27.8
Requires-Dist: pandas
